location/__init__.py
location/admin.py
location/apps.py
location/dataloaders.py
location/gql_mutations.py
location/gql_queries.py
location/models.py
location/schema.py
location/services.py
location/test_helpers.py
location/urls.py
location/views.py
location/migrations/0001_initial.py
location/migrations/0002_location.py
location/migrations/0003_userdistrict.py
location/migrations/0004_locationmutation.py
location/migrations/0005_20191212_1415.py
location/migrations/0006_users_api.py
location/migrations/0007_auto_20211103_1046.py
location/migrations/0008_add_enrollment_officer_gql_query_location_right.py
location/migrations/0009_add_location_read_right.py
location/migrations/0010_insert_create_region_location_perms.py
location/migrations/0011_auto_20230317_0924.py
location/migrations/0012_auto_20230317_0927.py
location/migrations/0013_auto_20230317_1534.py
location/migrations/0014_add_missing_fields_to_django_scheme.py
location/migrations/0015_set_managed_to_true.py
location/migrations/0016_auto_20230816_0934.py
location/migrations/0017_healthfacility_status.py
location/migrations/0018_auto_20230925_2243.py
location/migrations/0019_alter_location_code.py
location/migrations/__init__.py
location/tests/__init__.py
location/tests/test.py
location/tests/test_graphql.py
openimis_be_location-1.10.0.dist-info/licenses/LICENSE.md
openimis_be_location-1.10.0.dist-info/METADATA
openimis_be_location-1.10.0.dist-info/WHEEL
openimis_be_location-1.10.0.dist-info/top_level.txt
openimis_be_location-1.10.0.dist-info/RECORD
